hashkernel/__init__.py
hashkernel/auto_wire.py
hashkernel/base_x.py
hashkernel/cli.py
hashkernel/docs.py
hashkernel/executible.py
hashkernel/file_types.json
hashkernel/file_types.py
hashkernel/files.py
hashkernel/hashing.py
hashkernel/kernel.py
hashkernel/log_box.py
hashkernel/logic.py
hashkernel/otable.py
hashkernel/packer.py
hashkernel/plugins.py
hashkernel/smattr.py
hashkernel/time.py
hashkernel/typings.py
hashkernel/bakery/__init__.py
hashkernel/bakery/aio_client.py
hashkernel/bakery/aio_server.py
hashkernel/bakery/cask.py
hashkernel/bakery/kernel.py
hashkernel/bakery/msg_server.py
hashkernel/bakery/path.py
hashkernel/bakery/rack.py
hashkernel-2019.10.dist-info/LICENSE
hashkernel-2019.10.dist-info/METADATA
hashkernel-2019.10.dist-info/WHEEL
hashkernel-2019.10.dist-info/entry_points.txt
hashkernel-2019.10.dist-info/top_level.txt
hashkernel-2019.10.dist-info/RECORD
